kloudplugin/__init__.py
kloudplugin/_version.py
kloudplugin-0.1.1.data/data/share/jupyter/labextensions/kloudplugin/package.json
kloudplugin-0.1.1.data/data/share/jupyter/labextensions/kloudplugin/schemas/kloudplugin/package.json.orig
kloudplugin-0.1.1.data/data/share/jupyter/labextensions/kloudplugin/schemas/kloudplugin/plugin.json
kloudplugin-0.1.1.data/data/share/jupyter/labextensions/kloudplugin/static/509.dd8b7fcfe3e4ddfd0e55.js
kloudplugin-0.1.1.data/data/share/jupyter/labextensions/kloudplugin/static/728.a8c97a6d68a33769b988.js
kloudplugin-0.1.1.data/data/share/jupyter/labextensions/kloudplugin/static/remoteEntry.f0b08a50cf904d0dfffc.js
kloudplugin-0.1.1.data/data/share/jupyter/labextensions/kloudplugin/static/style.js
kloudplugin-0.1.1.data/data/share/jupyter/labextensions/kloudplugin/static/third-party-licenses.json
kloudplugin-0.1.1.data/data/share/jupyter/labextensions/kloudplugin/install.json
kloudplugin-0.1.1.dist-info/METADATA
kloudplugin-0.1.1.dist-info/WHEEL
kloudplugin-0.1.1.dist-info/licenses/LICENSE
kloudplugin-0.1.1.dist-info/RECORD
